[
	{
		"trigger": "enter",
		"cues": [
			{
				"text": "Graham! Co tu si\u0119 do licha dzieje?!",
				"who": "Kindle",
				"pause": 0.5,
				"time": 3.0
			},
			{
				"text": "Gremliny!",
				"who": "Graham",
				"pause": 0.5,
				"time": 3.0
			},
			{
				"text": "Gremliny?! \u017barty sobie robisz.",
				"who": "Kindle",
				"pause": 0.5,
				"time": 3.0
			},
			{
				"text": "Grendale jest oblegane przez gremilny, mieszka\u0144cy potrzebuj\u0105 Twojej pomocy.",
				"who": "Graham",
				"pause": 0.5,
				"time": 3.0
			},
			{
				"text": "Spoko, Wick i ja si\u0119 tym zajmiemy.",
				"who": "Kindle",
				"pause": 0.5,
				"time": 3.0
			}
		],
		"triggered": false,
		"stage": "Stage_0_H1"
	},
	{
		"trigger": "enter",
		"cues": [
			{
				"text": "Okr\u0119ty gremlin\u00f3w ostrzeliwuj\u0105 miasto.",
				"who": "Wick",
				"pause": 0.5,
				"time": 3.0
			},
			{
				"text": "Wygl\u0105da na porz\u0105dn\u0105 inwazj\u0119.",
				"who": "Kindle",
				"pause": 0.5,
				"time": 3.0
			},
			{
				"text": "Gnomi alarm! Bra\u0107 ich, ch\u0142opaki!",
				"who": "Scout",
				"pause": 0.5,
				"time": 3.0
			}
		],
		"triggered": false,
		"stage": "stage1"
	},
	{
		"trigger": "man3",
		"cues": [
			{
				"text": "Kindle, ocal ludno\u015b\u0107 Grendale.",
				"who": "Graham",
				"pause": 0.5,
				"time": 3.0
			}
		],
		"triggered": false,
		"stage": "Stage_0_H1"
	},
	{
		"trigger": "girl_1",
		"cues": [
			{
				"text": "U mie na podw\u00f3rku jezd taka no, studnia od \u017cycze\u0144.",
				"who": "Villager2",
				"pause": 0.5,
				"time": 3.0
			}
		],
		"triggered": false,
		"stage": "Stage_1_H1"
	},
	{
		"trigger": "male_1",
		"cues": [
			{
				"text": "Coby og\u0142uszy\u0107 wroga, wal wi\u0119cej z ramienia.",
				"who": "Villager1",
				"pause": 0.5,
				"time": 3.0
			}
		],
		"triggered": false,
		"stage": "Stage_1_H2"
	},
	{
		"trigger": "male_2",
		"cues": [
			{
				"text": "Donguri s\u0105 marzeniem odkrywcy.",
				"who": "Villager1",
				"pause": 0.5,
				"time": 3.0
			}
		],
		"triggered": false,
		"stage": "Stage_1_H3"
	},
	{
		"trigger": "male_3",
		"cues": [
			{
				"text": "Jak siem w domu \u015bwiat\u0142a palom, to ju\u017ce bezpieczny jezd.",
				"who": "Villager1",
				"pause": 0.5,
				"time": 3.0
			}
		],
		"triggered": false,
		"stage": "Stage_2_H1"
	},
	{
		"trigger": "male_4",
		"cues": [
			{
				"text": "\u015awietliki jarz\u0105 si\u0119 w pobli\u017cu sekret\u00f3w.",
				"who": "Villager1",
				"pause": 0.5,
				"time": 3.0
			}
		],
		"triggered": false,
		"stage": "Stage_2_H2"
	},
	{
		"trigger": "girl_2",
		"cues": [
			{
				"text": "Nie nara\u017caj si\u0119 Skrzatom, je\u015bli chcesz by ci pomog\u0142y.",
				"who": "Villager2",
				"pause": 0.5,
				"time": 3.0
			}
		],
		"triggered": false,
		"stage": "Stage_2_H3"
	},
	{
		"trigger": "girl_3",
		"cues": [
			{
				"text": "Moja przyjaci\u00f3\u0142ka Sue przeprowadzi\u0142a si\u0119 do wioski Mimiga.",
				"who": "Villager2",
				"pause": 0.5,
				"time": 3.0
			}
		],
		"triggered": false,
		"stage": "Stage_2_H4"
	},
	{
		"trigger": "male_5",
		"cues": [
			{
				"text": "W wirze walki twoja laska potrafi zdzia\u0142a\u0107 cuda.",
				"who": "Villager1",
				"pause": 0.5,
				"time": 3.0
			}
		],
		"triggered": false,
		"stage": "Stage_2_H4"
	}
]